frolic/__init__.py
frolic/console_printer.py
frolic/game.py
frolic/game_object.py
frolic/input_controller.py
frolic/matrix.py
frolic/matrix_border.py
frolic/screen.py
frolic/utils.py
frolic/vector2.py
frolic_engine-1.0.2.dist-info/LICENSE
frolic_engine-1.0.2.dist-info/METADATA
frolic_engine-1.0.2.dist-info/WHEEL
frolic_engine-1.0.2.dist-info/top_level.txt
frolic_engine-1.0.2.dist-info/RECORD
