Metadata-Version: 2.1
Name: frolic-engine
Version: 1.0.2
Summary: A game engine that lets you write text/ansii based games, targets 60fps.
Home-page: https://github.com/nateonguitar/FrolicEngine
Author: Nate Brooks
Author-email: nateonguitar@gmail.com
License: MIT
Keywords: game games engine text based frolic
Platform: UNKNOWN
Classifier: Intended Audience :: Developers
Classifier: Programming Language :: Python :: 3.9
Classifier: License :: OSI Approved :: MIT License
Classifier: Operating System :: OS Independent
License-File: LICENSE
Requires-Dist: pynput
Requires-Dist: numpy
Requires-Dist: colorama
